Xpress_parse/__init__.py
Xpress_parse/collect.py
Xpress_parse/labels.py
Xpress_parse/progress.py
Xpress_parse/records.py
Xpress_parse/users.py
Xpress_parse/write.py
Xpress_parse/xpress.py
Xpress_parse/scripts/__init__.py
Xpress_parse/scripts/_standalone_xpress_parse.py
Xpress_parse/test/__init__.py
Xpress_parse/test/test_collect.py
Xpress_parse/test/test_labels.py
Xpress_parse/test/test_progress.py
Xpress_parse/test/test_records.py
Xpress_parse/test/test_users.py
Xpress_parse/test/test_write.py
Xpress_parse-1.3.dist-info/LICENCE
Xpress_parse-1.3.dist-info/METADATA
Xpress_parse-1.3.dist-info/WHEEL
Xpress_parse-1.3.dist-info/entry_points.txt
Xpress_parse-1.3.dist-info/top_level.txt
Xpress_parse-1.3.dist-info/RECORD
