Metadata-Version: 2.1
Name: Xpress-parse
Version: 1.3
Summary: Help a user parse and select (and label) papers searched on Web Of Science based on their abstracts.
Home-page: https://github.com/FranckLejzerowicz/Xpress_parse
Author: Franck Lejzerowicz
Author-email: franck.lejzerowicz@gmail.com
Maintainer: Franck Lejzerowicz
Maintainer-email: franck.lejzerowicz@gmail.com
License: BSD
Platform: UNKNOWN
Classifier: License :: OSI Approved :: BSD License
Classifier: Topic :: Scientific/Engineering
Classifier: Topic :: Scientific/Engineering :: Bio-Informatics
Classifier: Programming Language :: Python :: 3.5
Classifier: Programming Language :: Python :: 3 :: Only
Classifier: Operating System :: Unix
Classifier: Operating System :: POSIX
Classifier: Operating System :: MacOS :: MacOS X
Requires-Python: >=3.6
License-File: LICENCE
Requires-Dist: click
Requires-Dist: pandas
Requires-Dist: numpy
